{
  "id": "foundry-vtt-mirror-image",
  "title": "Dnd5e Mirror Image",
  "description": "Simple module to handle the mirror image spell",
  "version": "#{VERSION}#",
  "authors": [
    {
      "name": "Paul Potsides",
      "flags": {}
    }
  ],
  "socket": true,
  "esmodules": [
    "scripts/index.mjs"
  ],
	"url": "#{URL}#",
	"manifest": "#{MANIFEST}#",
	"download": "#{DOWNLOAD}#",
  "compatibility": {
    "minimum": "11",
    "verified": "13",
    "maximum": "13"
  },
  "relationships": {
    "requires": [
      {
        "id": "tokenmagic",
        "type": "module",
        "manifest": "https://raw.githubusercontent.com/Feu-Secret/Tokenmagic/master/tokenmagic/module.json",
        "compatibility": {
          "minimum": "0.6.1.2",
          "verified": "0.6.9"
        }
      }
    ]
  }
}